wizard/__init__.py
wizard/__main__.py
wizard/exec.py
wizard/log.py
wizard/settings.py
nixos_wizard-0.1.1.dist-info/LICENSE
nixos_wizard-0.1.1.dist-info/METADATA
nixos_wizard-0.1.1.dist-info/WHEEL
nixos_wizard-0.1.1.dist-info/entry_points.txt
nixos_wizard-0.1.1.dist-info/top_level.txt
nixos_wizard-0.1.1.dist-info/RECORD
